{
  "url": "/struggles-of-undocumented-immigrants/index.html",
  "metadata": {
    "title": "Struggles of Undocumented Immigrants? - Vasquez Law Firm, PLLC",
    "metaDescription": "Learn the hidden causes of mental health struggles faced by undocumented immigrants. Discover expert solutions for better emotional well-being.",
    "metaKeywords": "",
    "canonical": "index.html",
    "ogTitle": "Struggles of Undocumented Immigrants? - Vasquez Law Firm, PLLC",
    "ogDescription": "Learn the hidden causes of mental health struggles faced by undocumented immigrants. Discover expert solutions for better emotional well-being.",
    "ogImage": "https://www.vasquezlawnc.com/wp-content/uploads/2025/01/Whats-Really-Behind-the-Mental-Health-Struggles.jpg",
    "structuredData": [
      {
        "@context": "https://schema.org",
        "@graph": [
          {
            "@type": "WebPage",
            "@id": "https://www.vasquezlawnc.com/struggles-of-undocumented-immigrants/",
            "url": "https://www.vasquezlawnc.com/struggles-of-undocumented-immigrants/",
            "name": "Struggles of Undocumented Immigrants? - Vasquez Law Firm, PLLC",
            "isPartOf": {
              "@id": "https://www.vasquezlawnc.com/#website"
            },
            "primaryImageOfPage": {
              "@id": "https://www.vasquezlawnc.com/struggles-of-undocumented-immigrants/#primaryimage"
            },
            "image": {
              "@id": "https://www.vasquezlawnc.com/struggles-of-undocumented-immigrants/#primaryimage"
            },
            "thumbnailUrl": "https://www.vasquezlawnc.com/wp-content/uploads/2025/01/Whats-Really-Behind-the-Mental-Health-Struggles.jpg",
            "datePublished": "2025-01-30T15:09:33+00:00",
            "author": {
              "@id": "https://www.vasquezlawnc.com/#/schema/person/2fa7514bdc81d9bc9644faadb9c7084f"
            },
            "description": "Learn the hidden causes of mental health struggles faced by undocumented immigrants. Discover expert solutions for better emotional well-being.",
            "breadcrumb": {
              "@id": "https://www.vasquezlawnc.com/struggles-of-undocumented-immigrants/#breadcrumb"
            },
            "inLanguage": "en-US",
            "potentialAction": [
              {
                "@type": "ReadAction",
                "target": ["https://www.vasquezlawnc.com/struggles-of-undocumented-immigrants/"]
              }
            ]
          },
          {
            "@type": "ImageObject",
            "inLanguage": "en-US",
            "@id": "https://www.vasquezlawnc.com/struggles-of-undocumented-immigrants/#primaryimage",
            "url": "https://www.vasquezlawnc.com/wp-content/uploads/2025/01/Whats-Really-Behind-the-Mental-Health-Struggles.jpg",
            "contentUrl": "https://www.vasquezlawnc.com/wp-content/uploads/2025/01/Whats-Really-Behind-the-Mental-Health-Struggles.jpg",
            "width": 600,
            "height": 400,
            "caption": "Image of an undocumented immigrant facing mental health struggles, highlighting the emotional and legal challenges they endure."
          },
          {
            "@type": "BreadcrumbList",
            "@id": "https://www.vasquezlawnc.com/struggles-of-undocumented-immigrants/#breadcrumb",
            "itemListElement": [
              {
                "@type": "ListItem",
                "position": 1,
                "name": "Home",
                "item": "https://www.vasquezlawnc.com/"
              },
              {
                "@type": "ListItem",
                "position": 2,
                "name": "Struggles of Undocumented Immigrants?"
              }
            ]
          },
          {
            "@type": "WebSite",
            "@id": "https://www.vasquezlawnc.com/#website",
            "url": "https://www.vasquezlawnc.com/",
            "name": "Vasquez Law Firm, PLLC",
            "description": "Raleigh, NC Immigration Attorney",
            "potentialAction": [
              {
                "@type": "SearchAction",
                "target": {
                  "@type": "EntryPoint",
                  "urlTemplate": "https://www.vasquezlawnc.com/?s={search_term_string}"
                },
                "query-input": {
                  "@type": "PropertyValueSpecification",
                  "valueRequired": true,
                  "valueName": "search_term_string"
                }
              }
            ],
            "inLanguage": "en-US"
          },
          {
            "@type": "Person",
            "@id": "https://www.vasquezlawnc.com/#/schema/person/2fa7514bdc81d9bc9644faadb9c7084f",
            "name": "wvasquez@vasquezlawfirm.com",
            "image": {
              "@type": "ImageObject",
              "inLanguage": "en-US",
              "@id": "https://www.vasquezlawnc.com/#/schema/person/image/",
              "url": "https://secure.gravatar.com/avatar/3ffe54679303fa3618cce95dfbfbfb41e698dfeba8e2eeae67ca5cfd8c1ecdbc?s=96&d=mm&r=g",
              "contentUrl": "https://secure.gravatar.com/avatar/3ffe54679303fa3618cce95dfbfbfb41e698dfeba8e2eeae67ca5cfd8c1ecdbc?s=96&d=mm&r=g",
              "caption": "wvasquez@vasquezlawfirm.com"
            },
            "url": "https://www.vasquezlawnc.com/author/wvasquezvasquezlawfirm-com/"
          }
        ]
      },
      {
        "@context": "https://schema.org",
        "@type": "LegalService",
        "@id": "https://vasquezlawnc.com/#organization",
        "name": "Vasquez Law Firm, PLLC",
        "alternateName": "Vasquez Law",
        "url": "https://vasquezlawnc.com",
        "logo": "https://vasquezlawnc.com/images/logo.png",
        "sameAs": [
          "https://www.facebook.com/vasquezlawfirm",
          "https://twitter.com/vasquezlawfirm",
          "https://www.linkedin.com/company/vasquez-law-firm"
        ],
        "contactPoint": {
          "@type": "ContactPoint",
          "telephone": "+1-844-967-3536",
          "contactType": "customer service",
          "availableLanguage": ["English", "Spanish"]
        }
      },
      {
        "@context": "https://schema.org",
        "@type": "BreadcrumbList",
        "itemListElement": [
          {
            "@type": "ListItem",
            "position": 1,
            "name": "Home",
            "item": "https://vasquezlawnc.com"
          },
          {
            "@type": "ListItem",
            "position": 2,
            "name": "Struggles of undocumented immigrants",
            "item": "https://vasquezlawnc.com/struggles-of-undocumented-immigrants"
          }
        ]
      },
      {
        "@context": "https://schema.org",
        "@type": "LegalService",
        "name": "Vasquez Law Firm",
        "aggregateRating": {
          "@type": "AggregateRating",
          "ratingValue": "4.8",
          "reviewCount": "127",
          "bestRating": "5"
        }
      }
    ]
  },
  "content": {
    "h1": "What’s Really Behind the Mental Health Struggles of Undocumented Immigrants?",
    "heroSection": "",
    "mainContent": "\n    <div class=\"et-l et-l--body\">\n\t\t\t<div class=\"et_builder_inner_content et_pb_gutters3\"><div class=\"et_pb_section et_pb_section_0_tb_body et_section_regular\">\n\t\t\t\t\n\t\t\t\t\n\t\t\t\t\n\t\t\t\t\n\t\t\t\t\n\t\t\t\t\n\t\t\t\t<div class=\"et_pb_row et_pb_row_0_tb_body\">\n\t\t\t\t<div class=\"et_pb_column et_pb_column_3_4 et_pb_column_0_tb_body  et_pb_css_mix_blend_mode_passthrough\">\n\t\t\t\t\n\t\t\t\t\n\t\t\t\t\n\t\t\t\t\n\t\t\t\t<div class=\"et_pb_module et_pb_post_title et_pb_post_title_0_tb_body et_pb_bg_layout_light  et_pb_text_align_left\">\n\t\t\t\t\n\t\t\t\t\n\t\t\t\t\n\t\t\t\t\n\t\t\t\t\n\t\t\t\t<div class=\"et_pb_title_container\">\n\t\t\t\t\t\n\t\t\t\t</div>\n\t\t\t\t\n\t\t\t</div><div class=\"et_pb_with_border et_pb_module et_pb_image et_pb_image_0_tb_body\">\n\t\t\t\t\n\t\t\t\t\n\t\t\t\t\n\t\t\t\t\n\t\t\t\t<span class=\"et_pb_image_wrap \"><img decoding=\"async\" width=\"600\" height=\"400\" src=\"../wp-content/uploads/2025/01/Whats-Really-Behind-the-Mental-Health-Struggles.jpg\" alt=\"Image of an undocumented immigrant facing mental health struggles, highlighting the emotional and legal challenges they endure.\" title=\"What’s Really Behind the Mental Health Struggles\" srcset=\"../wp-content/uploads/2025/01/Whats-Really-Behind-the-Mental-Health-Struggles.jpg 600w, ../wp-content/uploads/2025/01/Whats-Really-Behind-the-Mental-Health-Struggles-480x320.jpg 480w\" sizes=\"(min-width: 0px) and (max-width: 480px) 480px, (min-width: 481px) 600px, 100vw\" class=\"wp-image-4227\"></span>\n\t\t\t</div><div class=\"et_pb_module et_pb_post_content et_pb_post_content_0_tb_body\">\n\t\t\t\t\n\t\t\t\t\n\t\t\t\t\n\t\t\t\t\n\t\t\t\t<h1><b>What’s Really Behind the Mental Health Struggles of Undocumented Immigrants?</b></h1>\n<p><span style=\"font-weight: 400;\">Making the decision to migrate takes courage, but living without legal status in a new country adds immense emotional weight. The pressure of uncertainty, fear of deportation, and barriers to basic rights are a constant battle for many undocumented immigrants.</span></p>\n<p><span style=\"font-weight: 400;\">The emotional toll is heavy, yet understanding the root causes can help uncover ways to offer better support and solutions. Let’s explore the key factors behind these mental health challenges and what can be done to promote well-being.</span></p>\n<h2><b>The Weight of Living in the Shadows</b></h2>\n<p><span style=\"font-weight: 400;\">Many undocumented immigrants live under a cloud of fear. The lack of legal status makes even routine activities, like driving or applying for a job, a source of anxiety. This constant vigilance contributes to a chronic state of stress.</span></p>\n<h3><b>Common Triggers of Stress and Anxiety</b></h3>\n<ul>\n<li style=\"font-weight: 400;\" aria-level=\"1\"><b>Fear of Deportation</b><span style=\"font-weight: 400;\">: Every knock on the door could mean separation from family or being sent back to an uncertain future.</span></li>\n<li style=\"font-weight: 400;\" aria-level=\"1\"><b>Financial Insecurity</b><span style=\"font-weight: 400;\">: Without access to stable jobs, many undocumented individuals struggle to provide basic needs for their families.</span></li>\n<li style=\"font-weight: 400;\" aria-level=\"1\"><b>Limited Access to Healthcare</b><span style=\"font-weight: 400;\">: Mental health services are often inaccessible, leaving many to suffer in silence.</span></li>\n</ul>\n<h2><b>The Impact on Emotional Well-Being</b></h2>\n<p><span style=\"font-weight: 400;\">The strain of living as an undocumented immigrant doesn’t just affect daily life. It deeply influences emotional health, often leading to conditions like anxiety, depression, and post-traumatic stress disorder (PTSD).</span></p>\n<h3><b>Why Emotional Challenges Are Common</b></h3>\n<ul>\n<li style=\"font-weight: 400;\" aria-level=\"1\"><b>Isolation and Loneliness</b><span style=\"font-weight: 400;\">: Fear of exposure makes it difficult to build supportive social networks.</span></li>\n<li style=\"font-weight: 400;\" aria-level=\"1\"><b>Guilt and Shame</b><span style=\"font-weight: 400;\">: Many feel they’re a burden on their families or communities.</span></li>\n<li style=\"font-weight: 400;\" aria-level=\"1\"><b>Constant Uncertainty</b><span style=\"font-weight: 400;\">: Living without clear rights or a path to citizenship creates emotional instability.</span></li>\n</ul>\n<h2><b>The Hidden Consequences of Untreated Mental Health Issues</b></h2>\n<p><span style=\"font-weight: 400;\">When mental health is ignored, the effects ripple through every aspect of life. Relationships, job performance, and overall quality of life decline. Without intervention, emotional struggles can lead to severe consequences.</span></p>\n<h3><b>Risks of Neglected Mental Health</b></h3>\n<ol>\n<li style=\"font-weight: 400;\" aria-level=\"1\"><b>Decline in Physical Health</b><span style=\"font-weight: 400;\">: Chronic stress increases the risk of heart disease and other physical conditions.</span></li>\n<li style=\"font-weight: 400;\" aria-level=\"1\"><b>Substance Abuse</b><span style=\"font-weight: 400;\">: Some turn to alcohol or drugs as a coping mechanism.</span></li>\n<li style=\"font-weight: 400;\" aria-level=\"1\"><b>Family Strain</b><span style=\"font-weight: 400;\">: The burden of mental health struggles can cause tension and conflict in relationships.</span></li>\n</ol>\n<h2><b>How to Address Mental Health Needs</b></h2>\n<p><span style=\"font-weight: 400;\">Supporting undocumented immigrants begins with recognizing the unique challenges they face. While systemic change is necessary, there are immediate ways to promote emotional resilience.</span></p>\n<h3><b>Tips for Individuals and Families</b></h3>\n<ul>\n<li style=\"font-weight: 400;\" aria-level=\"1\"><b>Encourage Open Conversations</b><span style=\"font-weight: 400;\">: Creating safe spaces for dialogue helps reduce stigma.</span></li>\n<li style=\"font-weight: 400;\" aria-level=\"1\"><b>Learn Stress-Relief Techniques</b><span style=\"font-weight: 400;\">: Practices like meditation, breathing exercises, or regular physical activity can help.</span></li>\n<li style=\"font-weight: 400;\" aria-level=\"1\"><b>Build a Support Network</b><span style=\"font-weight: 400;\">: Finding community groups or trusted allies makes a significant difference.</span></li>\n</ul>\n<h3><b>Professional Resources and Community Support</b></h3>\n<ol>\n<li style=\"font-weight: 400;\" aria-level=\"1\"><b>Community Health Centers</b><span style=\"font-weight: 400;\">: Many offer low-cost or free mental health services.</span></li>\n<li style=\"font-weight: 400;\" aria-level=\"1\"><b>Legal Aid Organizations</b><span style=\"font-weight: 400;\">: Knowing one’s rights reduces fear and anxiety.</span></li>\n<li style=\"font-weight: 400;\" aria-level=\"1\"><b>Crisis Hotlines</b><span style=\"font-weight: 400;\">: Free confidential help is often available in multiple languages.</span></li>\n</ol>\n<h2><b>The Role of Advocacy and Policy Change</b></h2>\n<p><span style=\"font-weight: 400;\">Mental health support isn’t just an individual issue; it requires collective action. Advocating for fair policies and community support can create long-lasting change.</span></p>\n<h3><b>Steps Toward Change</b></h3>\n<ul>\n<li style=\"font-weight: 400;\" aria-level=\"1\"><b>Promote Access to Healthcare</b><span style=\"font-weight: 400;\">: Expanding mental health services for undocumented immigrants ensures fewer people are left behind.</span></li>\n<li style=\"font-weight: 400;\" aria-level=\"1\"><b>Support Pathways to Legalization</b><span style=\"font-weight: 400;\">: A clearer path to citizenship alleviates fear and provides stability.</span></li>\n<li style=\"font-weight: 400;\" aria-level=\"1\"><b>Raise Awareness</b><span style=\"font-weight: 400;\">: Public education on immigrant experiences builds empathy and reduces stigma.</span></li>\n</ul>\n<h2><b>Conclusion</b></h2>\n<p><span style=\"font-weight: 400;\">The emotional burdens faced by undocumented immigrants are profound, but they are not insurmountable. Through awareness, action, and compassionate support, we can foster a society that values mental well-being for all.</span></p>\n<p><span style=\"font-weight: 400;\">Taking steps to address these challenges today can create a better future where everyone, regardless of status, feels safe and supported in their pursuit of a brighter life.</span></p>\n<h3><b>Frequently Asked Questions</b></h3>\n<h3><span style=\"font-weight: 400;\">1. What are common mental health challenges faced by new migrants?</span></h3>\n<p><span style=\"font-weight: 400;\">Many migrants experience anxiety, depression, and chronic stress due to uncertainty and instability.</span></p>\n<h3><span style=\"font-weight: 400;\">2. How does legal uncertainty affect emotional health?</span></h3>\n<p><span style=\"font-weight: 400;\">Living in legal limbo creates ongoing fear and anxiety that can negatively impact mental health.</span></p>\n<h3><span style=\"font-weight: 400;\">3. Why is healthcare access limited for many migrants?</span></h3>\n<p><span style=\"font-weight: 400;\">Cost, language barriers, and fear of exposure often prevent migrants from seeking mental health care.</span></p>\n<h3><span style=\"font-weight: 400;\">4. Can lack of social connections worsen mental well-being?</span></h3>\n<p><span style=\"font-weight: 400;\">Yes, isolation and difficulty integrating into new communities can increase feelings of loneliness.</span></p>\n<h3><span style=\"font-weight: 400;\">5. How does family separation create psychological distress?</span></h3>\n<p><span style=\"font-weight: 400;\">The emotional pain of being apart from loved ones contributes to anxiety and depressive symptoms.</span></p>\n<h3><span style=\"font-weight: 400;\">6. What role does financial insecurity play in mental health struggles?</span></h3>\n<p><span style=\"font-weight: 400;\">Financial instability adds pressure, causing constant stress and worry about basic survival needs.</span></p>\n<h3><span style=\"font-weight: 400;\">7. How does stigma prevent migrants from seeking help?</span></h3>\n<p><span style=\"font-weight: 400;\">Cultural stigma and fear of judgment often discourage people from seeking mental health services.</span></p>\n<h3><span style=\"font-weight: 400;\">8. Do children in migrant families face mental health issues?</span></h3>\n<p><span style=\"font-weight: 400;\">Yes, children often experience stress from instability and fear of family separation.</span></p>\n<h3><span style=\"font-weight: 400;\">9. What coping strategies can help manage stress?</span></h3>\n<p><span style=\"font-weight: 400;\">Building supportive social networks, seeking professional help, and engaging in self-care are helpful.</span></p>\n<h3><span style=\"font-weight: 400;\">10. Are there resources available to support migrant mental health?</span></h3>\n<p><span style=\"font-weight: 400;\">Yes, local nonprofit organizations, legal aid services, and free counseling centers can offer assistance.</span></p>\n<p>&nbsp;</p>\n\n\t\t\t</div>\n\t\t\t</div><div class=\"et_pb_column et_pb_column_1_4 et_pb_column_1_tb_body  et_pb_css_mix_blend_mode_passthrough et-last-child\">\n\t\t\t\t\n\t\t\t\t\n\t\t\t\t\n\t\t\t\t\n\t\t\t\t<div class=\"et_pb_module et_pb_sidebar_0_tb_body et_pb_widget_area clearfix et_pb_widget_area_left et_pb_bg_layout_light et_pb_sidebar_no_border\">\n\t\t\t\t\n\t\t\t\t\n\t\t\t\t\n\t\t\t\t\n\t\t\t\t<div id=\"block-3\" class=\"et_pb_widget widget_block\">\n<div class=\"wp-block-group is-layout-flow wp-block-group-is-layout-flow\">\n<h2 class=\"wp-block-heading\">Recent Blog Posts</h2>\n\n\n<ul class=\"wp-block-latest-posts__list wp-block-latest-posts\"><li><a class=\"wp-block-latest-posts__post-title\" href=\"../best-workers-compensation-quote-save-more-today/index.html\">Best Workers Compensation Quote: Save More Today</a></li>\n<li><a class=\"wp-block-latest-posts__post-title\" href=\"../como-miles-se-han-beneficiado-al/index.html\">Cómo Miles se Han Beneficiado al</a></li>\n<li><a class=\"wp-block-latest-posts__post-title\" href=\"../como-navegar-las-complejidades-de-la-junta-de/index.html\">¿Cómo Navegar las Complejidades de la Junta de</a></li>\n<li><a class=\"wp-block-latest-posts__post-title\" href=\"index.html\">Struggles of Undocumented Immigrants?</a></li>\n<li><a class=\"wp-block-latest-posts__post-title\" href=\"../expert-tips-to-navigate-a-delayed-immigration-court-case-status/index.html\">Expert Tips to Navigate a Delayed Immigration Court Case Status</a></li>\n</ul></div>\n</div>\n\t\t\t</div>\n\t\t\t</div>\n\t\t\t\t\n\t\t\t\t\n\t\t\t\t\n\t\t\t\t\n\t\t\t</div>\n\t\t\t\t\n\t\t\t\t\n\t\t\t</div>\t\t</div>\n\t</div>\n\t    ",
    "sidebar": "",
    "breadcrumbs": ""
  },
  "navigation": {
    "mainMenu": [],
    "footerMenu": []
  },
  "forms": [],
  "images": [
    {
      "src": "../wp-content/uploads/2024/10/TRANSPARENT-WB-02-1.png",
      "alt": "El Mejor Abogado de Inmigración en Orlando: Defendiendo tus Derechos con Experiencia y Pasión",
      "title": "TRANSPARENT WB 02-1"
    },
    {
      "src": "https://vasquezlawnc.com/wp-content/uploads/2024/02/gold.png",
      "alt": "What’s Really Behind the Mental Health Struggles of Undocumented Immigrants? - general",
      "title": ""
    },
    {
      "src": "../wp-content/uploads/2025/01/Whats-Really-Behind-the-Mental-Health-Struggles.jpg",
      "alt": "Image of an undocumented immigrant facing mental health struggles, highlighting the emotional and legal challenges they endure.",
      "title": "What’s Really Behind the Mental Health Struggles"
    },
    {
      "src": "https://vasquezlawnc.com/wp-content/uploads/2024/02/lawpay.png",
      "alt": "What’s Really Behind the Mental Health Struggles of Undocumented Immigrants? - general",
      "title": "lawpay"
    },
    {
      "src": "https://vasquezlawnc.com/wp-content/uploads/2024/02/affirm-1.png",
      "alt": "What’s Really Behind the Mental Health Struggles of Undocumented Immigrants? - general",
      "title": "affirm"
    }
  ],
  "extractedAt": "2025-06-27T12:49:48.954Z",
  "contentSections": [],
  "internalLinks": [
    {
      "text": "Contact Us",
      "url": "/contact",
      "anchor": "Free Consultation"
    },
    {
      "text": "Our Attorneys",
      "url": "/attorneys",
      "anchor": "Meet Our Team"
    },
    {
      "text": "Practice Areas",
      "url": "/practice-areas",
      "anchor": "Legal Services"
    },
    {
      "text": "Green Card Services",
      "url": "/immigration/green-cards",
      "anchor": "Green Card Help"
    },
    {
      "text": "Citizenship",
      "url": "/immigration/citizenship",
      "anchor": "Become a Citizen"
    },
    {
      "text": "Visa Services",
      "url": "/immigration/visas",
      "anchor": "Visa Assistance"
    }
  ],
  "seoScore": 75,
  "pageType": "general",
  "enhancedAt": "2025-06-27T12:53:31.637Z",
  "seo": {
    "title": "immigration lawyer Charlotte NC | Vasquez Law Firm",
    "metaDescription": "immigration lawyer Charlotte NC. {\"h1\":\"What’s Really Behind the Mental Health Struggles of Undocumented Immigrants?\",\"heroSection\":\"\",\"mainContent\":\"\\n   ...",
    "keywords": "immigration lawyer Charlotte NC, immigration attorney near me, visa lawyer Charlotte, green card attorney, deportation defense lawyer, citizenship attorney Charlotte, DACA lawyer NC, asylum attorney, family immigration lawyer, work visa attorney Charlotte",
    "canonical": "https://vasquezlawnc.com/enhanced-complete/pages/struggles-of-undocumented-immigrants-",
    "robots": "index, follow",
    "og": {
      "title": "immigration lawyer Charlotte NC | Vasquez Law Firm",
      "description": "immigration lawyer Charlotte NC. {\"h1\":\"What’s Really Behind the Mental Health Struggles of Undocumented Immigrants?\",\"heroSection\":\"\",\"mainContent\":\"\\n   ...",
      "type": "website",
      "locale": "en_US"
    },
    "twitter": {
      "card": "summary_large_image",
      "site": "@VasquezLawFirm"
    }
  },
  "structuredData": {
    "@context": "https://schema.org",
    "@type": "LegalService",
    "name": "Vasquez Law Firm",
    "url": "https://vasquezlawnc.com",
    "logo": "https://vasquezlawnc.com/logo.png",
    "image": "https://vasquezlawnc.com/office.jpg",
    "telephone": "+1-844-967-3536",
    "email": "info@vasquezlawnc.com",
    "address": {
      "@type": "PostalAddress",
      "streetAddress": "4801 E Independence Blvd Suite 714",
      "addressLocality": "Charlotte",
      "addressRegion": "NC",
      "postalCode": "28212",
      "addressCountry": "US"
    },
    "geo": {
      "@type": "GeoCoordinates",
      "latitude": "35.1962",
      "longitude": "-80.7693"
    },
    "areaServed": [
      {
        "@type": "State",
        "name": "North Carolina"
      },
      {
        "@type": "State",
        "name": "South Carolina"
      }
    ],
    "openingHoursSpecification": [
      {
        "@type": "OpeningHoursSpecification",
        "dayOfWeek": ["Monday", "Tuesday", "Wednesday", "Thursday", "Friday"],
        "opens": "09:00",
        "closes": "18:00"
      }
    ],
    "priceRange": "$$",
    "paymentAccepted": ["Cash", "Check", "Credit Card", "PayPal"],
    "languages": ["English", "Spanish"],
    "serviceType": ["Immigration Law", "Visa Services", "Deportation Defense"],
    "mainEntity": {
      "@type": "FAQPage",
      "mainEntity": [
        {
          "@type": "Question",
          "name": "How long does the immigration process take?",
          "acceptedAnswer": {
            "@type": "Answer",
            "text": "Immigration timelines vary greatly depending on your case type. Green card applications can take 8-33 months, while citizenship typically takes 8-12 months. Contact Vasquez Law Firm for a personalized timeline assessment."
          }
        },
        {
          "@type": "Question",
          "name": "Do I need an immigration lawyer?",
          "acceptedAnswer": {
            "@type": "Answer",
            "text": "While not required, an immigration lawyer significantly improves your chances of success. Immigration law is complex and constantly changing. Our attorneys at Vasquez Law Firm ensure your application is complete and accurate."
          }
        },
        {
          "@type": "Question",
          "name": "How much does an immigration lawyer cost in Charlotte?",
          "acceptedAnswer": {
            "@type": "Answer",
            "text": "Immigration attorney fees vary by case complexity. Vasquez Law Firm offers competitive rates and payment plans. Call 1-844-YO-PELEO for a free consultation and fee quote."
          }
        }
      ]
    }
  },
  "optimizedContent": "[object Object]\n\n## Serving Charlotte and Surrounding Areas\nVasquez Law Firm proudly serves clients throughout Charlotte, Mecklenburg County, and the greater North Carolina area. With offices conveniently located in Charlotte, we're here to help with all your legal needs.\n\n\n## Why Choose Vasquez Law Firm?\n- **Experienced Attorneys**: Over 20 years of combined legal experience\n- **Bilingual Services**: We speak English and Spanish\n- **Free Consultation**: Call 1-844-YO-PELEO today\n- **Proven Results**: Hundreds of satisfied clients\n- **24/7 Availability**: We're here when you need us\n",
  "cta": {
    "primary": "Get Immigration Help Today",
    "secondary": "Schedule Your Free Consultation",
    "urgency": "Don't wait - immigration laws are changing. Call now!",
    "phone": "1-844-YO-PELEO"
  },
  "faqs": [
    {
      "question": "How long does the immigration process take?",
      "answer": "Immigration timelines vary greatly depending on your case type. Green card applications can take 8-33 months, while citizenship typically takes 8-12 months. Contact Vasquez Law Firm for a personalized timeline assessment."
    },
    {
      "question": "Do I need an immigration lawyer?",
      "answer": "While not required, an immigration lawyer significantly improves your chances of success. Immigration law is complex and constantly changing. Our attorneys at Vasquez Law Firm ensure your application is complete and accurate."
    },
    {
      "question": "How much does an immigration lawyer cost in Charlotte?",
      "answer": "Immigration attorney fees vary by case complexity. Vasquez Law Firm offers competitive rates and payment plans. Call 1-844-YO-PELEO for a free consultation and fee quote."
    }
  ]
}
