{
  "url": "https://www.vasquezlawnc.com/como-miles-se-han-beneficiado-al/",
  "path": "/como-miles-se-han-beneficiado-al/",
  "type": "blog-post",
  "fetchedAt": "2025-06-21T12:01:04.208Z",
  "title": "Cómo Miles se Han Beneficiado al - Vasquez Law Firm, PLLC",
  "metaDescription": "Descubre cómo miles se han beneficiado al entender la diferencia entre emigrar e inmigrar. ¡Toma una decisión informada sobre tu futuro hoy mismo!",
  "publishDate": "2025-02-07T12:17:03+00:00",
  "modifiedDate": "2025-04-23T13:35:21+00:00",
  "author": "wvasquez@vasquezlawfirm.com",
  "headline": "El Impacto de Tomar una Decisión Informada",
  "content": {
    "html": "",
    "text": "",
    "paragraphs": []
  },
  "categories": [],
  "tags": [],
  "featuredImage": "https://www.vasquezlawnc.com/wp-content/uploads/2025/02/12-1.jpg",
  "images": [],
  "relatedPosts": []
}
