{
  "url": "https://www.vasquezlawnc.com/struggles-of-undocumented-immigrants/",
  "path": "/struggles-of-undocumented-immigrants/",
  "type": "blog-post",
  "fetchedAt": "2025-06-21T12:01:14.714Z",
  "title": "Struggles of Undocumented Immigrants? - Vasquez Law Firm, PLLC",
  "metaDescription": "Learn the hidden causes of mental health struggles faced by undocumented immigrants. Discover expert solutions for better emotional well-being.",
  "publishDate": "2025-01-30T15:09:33+00:00",
  "modifiedDate": "",
  "author": "wvasquez@vasquezlawfirm.com",
  "headline": "What’s Really Behind the Mental Health Struggles of Undocumented Immigrants?",
  "content": {
    "html": "",
    "text": "",
    "paragraphs": []
  },
  "categories": [],
  "tags": [],
  "featuredImage": "https://www.vasquezlawnc.com/wp-content/uploads/2025/01/Whats-Really-Behind-the-Mental-Health-Struggles.jpg",
  "images": [],
  "relatedPosts": []
}
