{
  "title": "Notice Pursuant to the National Cooperative Research and Production Act of 1993-Integrated Photonics Institute for Manufacturing Innovation Operating Under the Name of the American Institute for Manufacturing Integrated Photonics",
  "agency": "Justice Department",
  "documentNumber": "2025-11308",
  "publicationDate": "2025-06-20",
  "summary": null,
  "url": "https://www.federalregister.gov/documents/2025/06/20/2025-11308/notice-pursuant-to-the-national-cooperative-research-and-production-act-of-1993-integrated-photonics",
  "processedAt": "2025-06-23T01:40:44.171Z"
}
